MANIFEST.in
README.rst
setup.py
django_werkzeug_debugger_runserver.egg-info/PKG-INFO
django_werkzeug_debugger_runserver.egg-info/SOURCES.txt
django_werkzeug_debugger_runserver.egg-info/dependency_links.txt
django_werkzeug_debugger_runserver.egg-info/requires.txt
django_werkzeug_debugger_runserver.egg-info/top_level.txt
werkzeug_debugger_runserver/__init__.py
werkzeug_debugger_runserver/management/__init__.py
werkzeug_debugger_runserver/management/commands/__init__.py
werkzeug_debugger_runserver/management/commands/runserver.py