Metadata-Version: 1.0
Name: django-werkzeug-debugger-runserver
Version: 0.2
Summary: Replaces Django's runserver command with one that includes the Werkzeug debugger (shamelessly ripped out of django-extensions)
Home-page: http://github.com/philippbosch/django-werkzeug-debugger-runserver
Author: Philipp Bosch and https://github.com/django-extensions/django-extensions/contributors
Author-email: hello@pb.io
License: BSD
Platform: UNKNOWN
